scale_json_binary/__init__.py
scale_json_binary/json_binary_codecs.py
scale_json_binary/py.typed
scale_json_binary-0.0.7.dist-info/METADATA
scale_json_binary-0.0.7.dist-info/WHEEL
scale_json_binary-0.0.7.dist-info/RECORD
