Metadata-Version: 2.1
Name: scale-json-binary
Version: 0.0.7
Summary: Codecs for json binary spec
Author: Michael Choi
Author-email: michael.choi@scale.com
Requires-Python: >=3.8,<4.0
Classifier: Programming Language :: Python :: 3
Classifier: Programming Language :: Python :: 3.8
Classifier: Programming Language :: Python :: 3.9
Classifier: Programming Language :: Python :: 3.10
Classifier: Programming Language :: Python :: 3.11
Requires-Dist: numpy (>=1.22.4)
Requires-Dist: ujson (>=5.7.0)
